Pyterate/__init__.py
Pyterate/ApiRstFactory/__init__.py
Pyterate/ApiRstFactory/templates/macros.jinja2
Pyterate/ApiRstFactory/templates/module.jinja2
Pyterate/ApiRstFactory/templates/toc.jinja2
Pyterate/Config/ConfigInstall.py
Pyterate/Config/__init__.py
Pyterate/Config/logging.yml
Pyterate/Jupyter/__init__.py
Pyterate/Logging/Logging.py
Pyterate/Logging/__init__.py
Pyterate/RstFactory/Document.py
Pyterate/RstFactory/RstFactory.py
Pyterate/RstFactory/Settings.py
Pyterate/RstFactory/Topic.py
Pyterate/RstFactory/__init__.py
Pyterate/RstFactory/Dom/Dom.py
Pyterate/RstFactory/Dom/FigureNodes.py
Pyterate/RstFactory/Dom/LitteralIncludeNodes.py
Pyterate/RstFactory/Dom/Markups.py
Pyterate/RstFactory/Dom/Registry.py
Pyterate/RstFactory/Dom/__init__.py
Pyterate/RstFactory/Dom/FigureGenerator/CircuitMacros.py
Pyterate/RstFactory/Dom/FigureGenerator/Generic.py
Pyterate/RstFactory/Dom/FigureGenerator/Tikz.py
Pyterate/RstFactory/Dom/FigureGenerator/__init__.py
Pyterate/RstFactory/Evaluator/FigureTools.py
Pyterate/RstFactory/Evaluator/NodeEvaluator.py
Pyterate/RstFactory/Evaluator/__init__.py
Pyterate/RstFactory/templates/document.jinja2
Pyterate/RstFactory/templates/document_base.jinja2
Pyterate/RstFactory/templates/macros.jinja2
Pyterate/RstFactory/templates/toc.jinja2
Pyterate/RstFactory/templates/toc_base.jinja2
Pyterate/Scripts/__init__.py
Pyterate/Scripts/circuit_macros_generator.py
Pyterate/Scripts/format_rst_table.py
Pyterate/Scripts/pyterate.py
Pyterate/Scripts/pyterate_rst_api.py
Pyterate/Template/Filters.py
Pyterate/Template/__init__.py
Pyterate/Tools/Generators.py
Pyterate/Tools/MarkupConverter.py
Pyterate/Tools/Timestamp.py
Pyterate/Tools/__init__.py
Pyterate-2.1.5.dist-info/LICENSE.txt
Pyterate-2.1.5.dist-info/METADATA
Pyterate-2.1.5.dist-info/WHEEL
Pyterate-2.1.5.dist-info/entry_points.txt
Pyterate-2.1.5.dist-info/top_level.txt
Pyterate-2.1.5.dist-info/RECORD
