Metadata-Version: 2.1
Name: Pyterate
Version: 2.1.5
Summary: Pyterate is a Sphinx add-ons to generate API documentation using autogen and litterate programming documentation for Python projects.
Home-page: https://github.com/FabriceSalvaire/Pyterate
Author: Fabrice SALVAIRE
Author-email: fabrice.salvaire@orange.fr
Maintainer: Fabrice SALVAIRE
Maintainer-email: fabrice.salvaire@orange.fr
License: GPLv3
Project-URL: Documentation, https://fabricesalvaire.github.io/Pyterate
Project-URL: Code, https://github.com/FabriceSalvaire/Pyterate
Project-URL: Issue Tracker, https://github.com/FabriceSalvaire/Pyterate/issues
Keywords: sphinx,autogen,documentation,generator,builder,literate,programming
Platform: any
Classifier: Development Status :: 5 - Production/Stable
Classifier: Framework :: Sphinx :: Extension
Classifier: Intended Audience :: Developers
Classifier: Intended Audience :: Education
Classifier: Intended Audience :: Science/Research
Classifier: License :: OSI Approved :: GNU General Public License v3 (GPLv3)
Classifier: Operating System :: OS Independent
Classifier: Programming Language :: Python :: 3.4
Classifier: Topic :: Software Development :: Documentation
Requires-Python: >=3.4
Requires-Dist: Jinja2
Requires-Dist: PyYAML (>=3.10)
Requires-Dist: jupyter
Requires-Dist: jupyter-client
Requires-Dist: nbformat
Requires-Dist: pypandoc (>=1.5)
Requires-Dist: sphinx (>=3)
Requires-Dist: sphinxcontrib-getthecode (>=1.2.1)
